langchain_ark/__init__.py
langchain_ark/chat_models.py
langchain_ark/embeddings.py
langchain_ark/llms.py
langchain_ark/py.typed
langchain_ark/utils.py
langchain_ark-0.1.5.dist-info/LICENSE
langchain_ark-0.1.5.dist-info/METADATA
langchain_ark-0.1.5.dist-info/WHEEL
langchain_ark-0.1.5.dist-info/RECORD
