Metadata-Version: 2.1
Name: langchain-ark
Version: 0.1.5
Summary: 
Author: zbmain
Author-email: zbmaincn@gmail.com
Requires-Python: >=3.10,<4.0
Classifier: Programming Language :: Python :: 3
Classifier: Programming Language :: Python :: 3.10
Classifier: Programming Language :: Python :: 3.11
Classifier: Programming Language :: Python :: 3.12
Requires-Dist: langchain-core (>=0.3.17,<0.4.0)
Requires-Dist: numpy (>=2.1.3,<3.0.0)
Requires-Dist: python-dotenv (>=1.0.1,<2.0.0)
Requires-Dist: volcengine-python-sdk[ark] (>=1.0.109,<2.0.0)
